zetsubou/__init__.py
zetsubou/__main__.py
zetsubou/_version.py
zetsubou/configuration.py
zetsubou/logo.py
zetsubou/zetsubou.py
zetsubou/zetsubou_conan_toolchain.py
zetsubou/commands/__init__.py
zetsubou/commands/base_command.py
zetsubou/commands/build.py
zetsubou/commands/clean.py
zetsubou/commands/clean_build.py
zetsubou/commands/command_context.py
zetsubou/commands/command_registry.py
zetsubou/commands/config.py
zetsubou/commands/create.py
zetsubou/commands/execute_stage.py
zetsubou/commands/generate.py
zetsubou/commands/install.py
zetsubou/commands/regen.py
zetsubou/conan/__init__.py
zetsubou/conan/conan.py
zetsubou/conan/dependencies.py
zetsubou/conan/deployer.py
zetsubou/conan/from_conan.py
zetsubou/conan/to_conan.py
zetsubou/data/__init__.py
zetsubou/data/rules/ClangRules.yml
zetsubou/data/rules/MsvcRules.yml
zetsubou/fastbuild/__init__.py
zetsubou/fastbuild/compiler.py
zetsubou/fastbuild/fastbuild_emit.py
zetsubou/fastbuild/target_kinds.py
zetsubou/fastbuild/to_fastbuild.py
zetsubou/fastbuild/vcxproject.py
zetsubou/fastbuild/vssolution.py
zetsubou/project/__init__.py
zetsubou/project/base_context.py
zetsubou/project/config_matrix.py
zetsubou/project/model/__init__.py
zetsubou/project/model/cli_tool.py
zetsubou/project/model/config_string.py
zetsubou/project/model/configuration.py
zetsubou/project/model/configuration_enums.py
zetsubou/project/model/filter.py
zetsubou/project/model/kind.py
zetsubou/project/model/platform.py
zetsubou/project/model/platform_enums.py
zetsubou/project/model/project_template.py
zetsubou/project/model/rule.py
zetsubou/project/model/runtime_library.py
zetsubou/project/model/target.py
zetsubou/project/model/toolchain.py
zetsubou/project/model/toolchain_enums.py
zetsubou/project/model/toolchain_profile.py
zetsubou/project/model/virtual_environment.py
zetsubou/project/runtime/__init__.py
zetsubou/project/runtime/emit.py
zetsubou/project/runtime/project_loader.py
zetsubou/project/runtime/resolve.py
zetsubou/project/runtime/validation.py
zetsubou-0.8.1.dist-info/METADATA
zetsubou-0.8.1.dist-info/WHEEL
zetsubou-0.8.1.dist-info/entry_points.txt
zetsubou-0.8.1.dist-info/top_level.txt
zetsubou-0.8.1.dist-info/RECORD
